LICENSE
README.md
setup.cfg
setup.py
a8a8a8a8a8a8a8a8a8a8a8a8a8a8a8.egg-info/PKG-INFO
a8a8a8a8a8a8a8a8a8a8a8a8a8a8a8.egg-info/SOURCES.txt
a8a8a8a8a8a8a8a8a8a8a8a8a8a8a8.egg-info/dependency_links.txt
a8a8a8a8a8a8a8a8a8a8a8a8a8a8a8.egg-info/top_level.txt
audiobook/__init__.py
tests/__init__.py
tests/test.py
tests/test_audiobook.py