Metadata-Version: 2.1
Name: a8a8a8a8a8a8a8a8a8a8a8a8a8a8a8
Version: 1.0.4
Summary: Listen to your favourite audiobook
Home-page: https://github.com/JoeAmedeo/audiobook
Author: JoeAmedeo
Author-email: joseph.p.amedeo@gmail.com
License: UNKNOWN
Keywords: audiobook
Platform: UNKNOWN
Classifier: Development Status :: 3 - Alpha
Classifier: Programming Language :: Python :: 3
Classifier: License :: OSI Approved :: MIT License
Classifier: Operating System :: OS Independent
Classifier: Intended Audience :: End Users/Desktop
Classifier: Intended Audience :: Developers
Requires-Python: >=3.4
